pathways_ensemble_analysis/__init__.py
pathways_ensemble_analysis/_version.py
pathways_ensemble_analysis/assessment.py
pathways_ensemble_analysis/evaluation.py
pathways_ensemble_analysis/plot.py
pathways_ensemble_analysis/utils.py
pathways_ensemble_analysis/criteria/__init__.py
pathways_ensemble_analysis/criteria/base.py
pathways_ensemble_analysis/criteria/library.py
pathways_ensemble_analysis-1.0.0.dist-info/LICENSE.txt
pathways_ensemble_analysis-1.0.0.dist-info/METADATA
pathways_ensemble_analysis-1.0.0.dist-info/WHEEL
pathways_ensemble_analysis-1.0.0.dist-info/top_level.txt
pathways_ensemble_analysis-1.0.0.dist-info/RECORD
