Metadata-Version: 2.1
Name: pathways-ensemble-analysis
Version: 1.0.0
Summary: Multi-criteria pathways ensemble analysis
Home-page: https://gitlab.com/climateanalytics/pathways-ensemble-analysis
Author: Climate Analytics Modelling & Mitigation Team
Author-email: cpt-tools@climateanalytics.org
License: MIT
Platform: any
Classifier: Development Status :: 4 - Beta
Classifier: Programming Language :: Python
License-File: LICENSE.txt
Requires-Dist: importlib-metadata ; python_version < "3.8"
Provides-Extra: testing
Requires-Dist: setuptools ; extra == 'testing'
Requires-Dist: pytest ; extra == 'testing'
Requires-Dist: pytest-cov ; extra == 'testing'
